pyflexcfg/__init__.py
pyflexcfg/components/__init__.py
pyflexcfg/components/abstractclasses.py
pyflexcfg/components/constants.py
pyflexcfg/components/encryption.py
pyflexcfg/components/metaclasses.py
pyflexcfg/components/misc.py
pyflexcfg/components/yaml_loader.py
pyflexcfg/config_handler.py
pyflexcfg-1.0.0.dist-info/LICENSE
pyflexcfg-1.0.0.dist-info/METADATA
pyflexcfg-1.0.0.dist-info/WHEEL
pyflexcfg-1.0.0.dist-info/RECORD
