Metadata-Version: 2.1
Name: pyflexcfg
Version: 1.0.0
Summary: Simple and flexible configuration handler for Python projects.
Home-page: https://github.com/pavelterex/PyFlexCfg
License: MIT
Author: Pavel T
Author-email: pavelterex@gmail.com
Requires-Python: >=3.10,<4.0
Classifier: Development Status :: 5 - Production/Stable
Classifier: Intended Audience :: Developers
Classifier: License :: OSI Approved :: MIT License
Classifier: Operating System :: OS Independent
Classifier: Programming Language :: Python :: 3
Classifier: Programming Language :: Python :: 3.10
Classifier: Programming Language :: Python :: 3.11
Classifier: Programming Language :: Python :: 3.12
Classifier: Programming Language :: Python :: 3.13
Requires-Dist: cryptography (>=43.0.3,<44.0.0)
Requires-Dist: pyyaml (>=6.0.2,<7.0.0)
Project-URL: Repository, https://github.com/pavelterex/PyFlexCfg
